eddy_squeeze/__init__.py
eddy_squeeze/eddy_squeeze.py
eddy_squeeze/eddy_squeeze_lib/__init__.py
eddy_squeeze/eddy_squeeze_lib/eddy_collect.py
eddy_squeeze/eddy_squeeze_lib/eddy_files.py
eddy_squeeze/eddy_squeeze_lib/eddy_present.py
eddy_squeeze/eddy_squeeze_lib/eddy_run_command.py
eddy_squeeze/eddy_squeeze_lib/eddy_utils.py
eddy_squeeze/eddy_squeeze_lib/eddy_web.py
eddy_squeeze/eddy_squeeze_lib/unused.py
eddy_squeeze/html_templates/base.html
eddy_squeeze/html_templates/base_study.html
eddy_squeeze/html_templates/pnl-bwh-hms.png
eddy_squeeze/html_templates/template.html
eddy_squeeze-1.0.0.data/scripts/eddy_squeeze
tests/__init__.py
tests/test_eddy_squeeze.py
eddy_squeeze-1.0.0.dist-info/LICENSE
eddy_squeeze-1.0.0.dist-info/METADATA
eddy_squeeze-1.0.0.dist-info/WHEEL
eddy_squeeze-1.0.0.dist-info/top_level.txt
eddy_squeeze-1.0.0.dist-info/RECORD
