Metadata-Version: 2.1
Name: eddy-squeeze
Version: 1.0.0
Summary: Visualize extra information from FSL 6.0.1 eddy outputs
Home-page: https://github.com/pnlbwh/eddy-squeeze
Author: Kevin Cho
Author-email: kevincho@bwh.harvard.edu
License: UNKNOWN
Platform: UNKNOWN
Classifier: Programming Language :: Python :: 3
Classifier: License :: OSI Approved :: MIT License
Requires-Python: >=3.7
Requires-Dist: tabulate (>=0.8.7)
Requires-Dist: matplotlib (>=3.0.3)
Requires-Dist: pandas (>=0.24)
Requires-Dist: numpy (>=1.1)
Requires-Dist: nibabel (>=3.1)
Requires-Dist: Jinja2 (>=2.0)
Requires-Dist: pathlib2 (>=2.3)
Requires-Dist: seaborn (>=0.9)
